pct_tools.libs/libgomp-a34b3233.so.1.0.0
pct_tools/io.py
pct_tools/__init__.py
pct_tools/mlp.py
pct_tools/_ext.cpython-312-x86_64-linux-gnu.so
pct_tools/utils.py
pct_tools/recon.py
pct_tools/matrix.py
pct_tools/lipschitz.py
include/eigen3/signature_of_eigen3_matrix_library
include/eigen3/Eigen/SuperLUSupport
include/eigen3/Eigen/Eigen
include/eigen3/Eigen/Geometry
include/eigen3/Eigen/Eigenvalues
include/eigen3/Eigen/CholmodSupport
include/eigen3/Eigen/StdList
include/eigen3/Eigen/Householder
include/eigen3/Eigen/SPQRSupport
include/eigen3/Eigen/PardisoSupport
include/eigen3/Eigen/MetisSupport
include/eigen3/Eigen/SparseQR
include/eigen3/Eigen/QR
include/eigen3/Eigen/LU
include/eigen3/Eigen/Cholesky
include/eigen3/Eigen/SparseLU
include/eigen3/Eigen/IterativeLinearSolvers
include/eigen3/Eigen/Core
include/eigen3/Eigen/SparseCholesky
include/eigen3/Eigen/Jacobi
include/eigen3/Eigen/StdDeque
include/eigen3/Eigen/StdVector
include/eigen3/Eigen/QtAlignedMalloc
include/eigen3/Eigen/PaStiXSupport
include/eigen3/Eigen/SparseCore
include/eigen3/Eigen/OrderingMethods
include/eigen3/Eigen/Dense
include/eigen3/Eigen/Sparse
include/eigen3/Eigen/UmfPackSupport
include/eigen3/Eigen/KLUSupport
include/eigen3/Eigen/SVD
include/eigen3/Eigen/src/SuperLUSupport/SuperLUSupport.h
include/eigen3/Eigen/src/StlSupport/StdVector.h
include/eigen3/Eigen/src/StlSupport/details.h
include/eigen3/Eigen/src/StlSupport/StdDeque.h
include/eigen3/Eigen/src/StlSupport/StdList.h
include/eigen3/Eigen/src/Geometry/Homogeneous.h
include/eigen3/Eigen/src/Geometry/RotationBase.h
include/eigen3/Eigen/src/Geometry/Rotation2D.h
include/eigen3/Eigen/src/Geometry/EulerAngles.h
include/eigen3/Eigen/src/Geometry/OrthoMethods.h
include/eigen3/Eigen/src/Geometry/Scaling.h
include/eigen3/Eigen/src/Geometry/Quaternion.h
include/eigen3/Eigen/src/Geometry/Hyperplane.h
include/eigen3/Eigen/src/Geometry/Transform.h
include/eigen3/Eigen/src/Geometry/Translation.h
pct_tools-0.4.1.dist-info/METADATA
pct_tools-0.4.1.dist-info/RECORD
pct_tools-0.4.1.dist-info/WHEEL
