Metadata-Version: 2.1
Name: pct-tools
Version: 0.4.1
Summary: Tools for proton CT reconstructions.
Author-Email: Matthieu Hentz <m.hentz@outlook.com>
Requires-Python: >=3.12
Requires-Dist: numpy>=1.26.0
Requires-Dist: scipy>=1.11.2
